data_modori/tools/__init__.py
data_modori/tools/analyze_data.py
data_modori/tools/process_data.py
py_data_modori-0.1.1.dist-info/LICENSE
py_data_modori-0.1.1.dist-info/METADATA
py_data_modori-0.1.1.dist-info/WHEEL
py_data_modori-0.1.1.dist-info/entry_points.txt
py_data_modori-0.1.1.dist-info/top_level.txt
py_data_modori-0.1.1.dist-info/RECORD
