Metadata-Version: 2.1
Name: py-data-modori
Version: 0.1.1
Summary: LMOps Tool for Korean
Home-page: https://github.com/teamreboott/data-modori
Author: TeamAR of Teamreboott
License: Apache License 2.0
Classifier: License :: OSI Approved :: Apache Software License
Classifier: Programming Language :: Python :: 3
Classifier: Operating System :: OS Independent
License-File: LICENSE
Requires-Dist: fsspec ==2023.3.0
Requires-Dist: pyarrow <=12.0.0
Requires-Dist: pandas ==2.0.0
Requires-Dist: datasets ==2.11.0
Requires-Dist: loguru
Requires-Dist: tabulate
Requires-Dist: tqdm
Requires-Dist: jsonargparse[signatures]
Requires-Dist: matplotlib
Requires-Dist: emoji ==2.2.0
Requires-Dist: regex
Requires-Dist: requests
Requires-Dist: wget
Requires-Dist: zstandard
Requires-Dist: lz4
Requires-Dist: pdfplumber
Requires-Dist: plotly
Requires-Dist: python-docx
Requires-Dist: streamlit
Requires-Dist: spacy ==3.5.0
Requires-Dist: multiprocess ==0.70.12
Requires-Dist: dill ==0.3.4
Requires-Dist: scipy
Requires-Dist: boto3
Requires-Dist: simhash-py
Requires-Dist: gluonnlp
Requires-Dist: mxnet
Requires-Dist: numpy ==1.23.1
Requires-Dist: selectolax
Requires-Dist: ftfy
Requires-Dist: nlpaug
Provides-Extra: all
Requires-Dist: fsspec ==2023.3.0 ; extra == 'all'
Requires-Dist: pyarrow <=12.0.0 ; extra == 'all'
Requires-Dist: pandas ==2.0.0 ; extra == 'all'
Requires-Dist: datasets ==2.11.0 ; extra == 'all'
Requires-Dist: loguru ; extra == 'all'
Requires-Dist: tabulate ; extra == 'all'
Requires-Dist: tqdm ; extra == 'all'
Requires-Dist: jsonargparse[signatures] ; extra == 'all'
Requires-Dist: matplotlib ; extra == 'all'
Requires-Dist: emoji ==2.2.0 ; extra == 'all'
Requires-Dist: regex ; extra == 'all'
Requires-Dist: requests ; extra == 'all'
Requires-Dist: wget ; extra == 'all'
Requires-Dist: zstandard ; extra == 'all'
Requires-Dist: lz4 ; extra == 'all'
Requires-Dist: pdfplumber ; extra == 'all'
Requires-Dist: plotly ; extra == 'all'
Requires-Dist: python-docx ; extra == 'all'
Requires-Dist: streamlit ; extra == 'all'
Requires-Dist: spacy ==3.5.0 ; extra == 'all'
Requires-Dist: multiprocess ==0.70.12 ; extra == 'all'
Requires-Dist: dill ==0.3.4 ; extra == 'all'
Requires-Dist: scipy ; extra == 'all'
Requires-Dist: boto3 ; extra == 'all'
Requires-Dist: simhash-py ; extra == 'all'
Requires-Dist: gluonnlp ; extra == 'all'
Requires-Dist: mxnet ; extra == 'all'
Requires-Dist: numpy ==1.23.1 ; extra == 'all'
Requires-Dist: selectolax ; extra == 'all'
Requires-Dist: ftfy ; extra == 'all'
Requires-Dist: nlpaug ; extra == 'all'
Requires-Dist: fasttext-wheel ; extra == 'all'
Requires-Dist: kenlm ; extra == 'all'
Requires-Dist: sentencepiece ; extra == 'all'
Requires-Dist: nlpcda ; extra == 'all'
Requires-Dist: nltk ; extra == 'all'
Requires-Dist: transformers ; extra == 'all'
Requires-Dist: opencc ==1.1.6 ; extra == 'all'
Requires-Dist: imagededup ; extra == 'all'
Requires-Dist: torch ; extra == 'all'
Requires-Dist: dlib ; extra == 'all'
Requires-Dist: spacy-pkuseg ==0.0.32 ; extra == 'all'
Requires-Dist: ray ; extra == 'all'
Requires-Dist: pre-commit ; extra == 'all'
Requires-Dist: sphinx ; extra == 'all'
Requires-Dist: sphinx-autobuild ; extra == 'all'
Requires-Dist: sphinx-rtd-theme ; extra == 'all'
Requires-Dist: recommonmark ; extra == 'all'
Requires-Dist: fire ; extra == 'all'
Requires-Dist: jsonlines ; extra == 'all'
Requires-Dist: pyspark ; extra == 'all'
Provides-Extra: dev
Requires-Dist: pre-commit ; extra == 'dev'
Requires-Dist: sphinx ; extra == 'dev'
Requires-Dist: sphinx-autobuild ; extra == 'dev'
Requires-Dist: sphinx-rtd-theme ; extra == 'dev'
Requires-Dist: recommonmark ; extra == 'dev'
Provides-Extra: dist
Requires-Dist: ray ; extra == 'dist'
Provides-Extra: mini
Requires-Dist: fsspec ==2023.3.0 ; extra == 'mini'
Requires-Dist: pyarrow <=12.0.0 ; extra == 'mini'
Requires-Dist: pandas ==2.0.0 ; extra == 'mini'
Requires-Dist: datasets ==2.11.0 ; extra == 'mini'
Requires-Dist: loguru ; extra == 'mini'
Requires-Dist: tabulate ; extra == 'mini'
Requires-Dist: tqdm ; extra == 'mini'
Requires-Dist: jsonargparse[signatures] ; extra == 'mini'
Requires-Dist: matplotlib ; extra == 'mini'
Requires-Dist: emoji ==2.2.0 ; extra == 'mini'
Requires-Dist: regex ; extra == 'mini'
Requires-Dist: requests ; extra == 'mini'
Requires-Dist: wget ; extra == 'mini'
Requires-Dist: zstandard ; extra == 'mini'
Requires-Dist: lz4 ; extra == 'mini'
Requires-Dist: pdfplumber ; extra == 'mini'
Requires-Dist: plotly ; extra == 'mini'
Requires-Dist: python-docx ; extra == 'mini'
Requires-Dist: streamlit ; extra == 'mini'
Requires-Dist: spacy ==3.5.0 ; extra == 'mini'
Requires-Dist: multiprocess ==0.70.12 ; extra == 'mini'
Requires-Dist: dill ==0.3.4 ; extra == 'mini'
Requires-Dist: scipy ; extra == 'mini'
Requires-Dist: boto3 ; extra == 'mini'
Requires-Dist: simhash-py ; extra == 'mini'
Requires-Dist: gluonnlp ; extra == 'mini'
Requires-Dist: mxnet ; extra == 'mini'
Requires-Dist: numpy ==1.23.1 ; extra == 'mini'
Requires-Dist: selectolax ; extra == 'mini'
Requires-Dist: ftfy ; extra == 'mini'
Requires-Dist: nlpaug ; extra == 'mini'
Provides-Extra: sci
Requires-Dist: fasttext-wheel ; extra == 'sci'
Requires-Dist: kenlm ; extra == 'sci'
Requires-Dist: sentencepiece ; extra == 'sci'
Requires-Dist: scipy ; extra == 'sci'
Requires-Dist: ftfy ; extra == 'sci'
Requires-Dist: simhash-py ; extra == 'sci'
Requires-Dist: selectolax ; extra == 'sci'
Requires-Dist: nlpaug ; extra == 'sci'
Requires-Dist: nlpcda ; extra == 'sci'
Requires-Dist: nltk ; extra == 'sci'
Requires-Dist: transformers ; extra == 'sci'
Requires-Dist: opencc ==1.1.6 ; extra == 'sci'
Requires-Dist: imagededup ; extra == 'sci'
Requires-Dist: torch ; extra == 'sci'
Requires-Dist: dlib ; extra == 'sci'
Requires-Dist: spacy-pkuseg ==0.0.32 ; extra == 'sci'
Provides-Extra: tools
Requires-Dist: fire ; extra == 'tools'
Requires-Dist: jsonlines ; extra == 'tools'
Requires-Dist: pyspark ; extra == 'tools'
Requires-Dist: wget ; extra == 'tools'
